options/__init__.py
options/admin.py
options/apps.py
options/models.py
options/urls.py
options/views.py
options/management/__init__.py
options/management/commands/__init__.py
options/management/commands/setoption.py
options/migrations/0001_initial.py
options/migrations/0002_auto_20181101_0047.py
options/migrations/0003_auto_20181101_2050.py
options/migrations/0004_option_public.py
options/migrations/__init__.py
django_runtime_options-0.1.3.dist-info/LICENSE
django_runtime_options-0.1.3.dist-info/METADATA
django_runtime_options-0.1.3.dist-info/WHEEL
django_runtime_options-0.1.3.dist-info/top_level.txt
django_runtime_options-0.1.3.dist-info/RECORD
