Metadata-Version: 2.1
Name: django-runtime-options
Version: 0.1.3
Summary: Penn Labs example description
Home-page: https://github.com/pennlabs/django-runtime-options
Author: Penn Labs
Author-email: admin@pennlabs.org
License: MIT
Project-URL: Changelog, https://github.com/pennlabs/django-runtime-options/blob/master/CHANGELOG.md
Platform: UNKNOWN
Classifier: Framework :: Django
Classifier: Programming Language :: Python
Classifier: Programming Language :: Python :: 3.6
Classifier: Programming Language :: Python :: 3.7
Classifier: Programming Language :: Python :: 3.8
Requires-Python: >=3.6
Requires-Dist: django (>=2.0.0)
